pa_ringbuffer.py
pa_ringbuffer-0.1.4.dist-info/LICENSE
pa_ringbuffer-0.1.4.dist-info/METADATA
pa_ringbuffer-0.1.4.dist-info/WHEEL
pa_ringbuffer-0.1.4.dist-info/top_level.txt
pa_ringbuffer-0.1.4.dist-info/RECORD
