Metadata-Version: 2.1
Name: pa-ringbuffer
Version: 0.1.4
Summary: Python wrapper for PortAudio's ring buffer
Home-page: https://github.com/spatialaudio/python-pa-ringbuffer
Author: Matthias Geier
Author-email: Matthias.Geier@gmail.com
License: MIT
Keywords: sound,audio,PortAudio,ringbuffer,lock-free
Platform: any
Classifier: License :: OSI Approved :: MIT License
Classifier: Operating System :: OS Independent
Classifier: Programming Language :: Python
Classifier: Programming Language :: Python :: 2
Classifier: Programming Language :: Python :: 3
Classifier: Topic :: Multimedia :: Sound/Audio
Requires-Python: >=2.6
